ufy/__init__.py
ufy/CV/__init__.py
ufy/core/__init__.py
ufy/core/dataStructure/__init__.py
ufy/core/dataStructure/graph/__init__.py
ufy/core/dataStructure/linkList/__init__.py
ufy/core/dataStructure/queue/__init__.py
ufy/core/dataStructure/queue/arrayQueue.py
ufy/core/dataStructure/stack/__init__.py
ufy/core/dataStructure/tree/__init__.py
ufy/core/np/__init__.py
ufy/core/np/activations.py
ufy-0.1.16.dist-info/METADATA
ufy-0.1.16.dist-info/WHEEL
ufy-0.1.16.dist-info/top_level.txt
ufy-0.1.16.dist-info/RECORD
