Metadata-Version: 2.1
Name: ufy
Version: 0.1.16
Summary: some tools for ufy
Home-page: UNKNOWN
Author: ufy
License: UNKNOWN
Platform: UNKNOWN
